eQuimageGtk/__init__.py
eQuimageGtk/eQuimage.py
eQuimageGtk/config/eQuimage.css
eQuimageGtk/config/eQuimage.mplstyle
eQuimageGtk/gui/base.py
eQuimageGtk/gui/editors.py
eQuimageGtk/gui/lightcurve.py
eQuimageGtk/gui/logs.py
eQuimageGtk/gui/luma.py
eQuimageGtk/gui/mainwindow.py
eQuimageGtk/gui/menus.py
eQuimageGtk/gui/settings.py
eQuimageGtk/gui/statistics.py
eQuimageGtk/gui/toolmanager.py
eQuimageGtk/gui/gtk/customwidgets.py
eQuimageGtk/gui/gtk/filechoosers.py
eQuimageGtk/gui/gtk/keyboard.py
eQuimageGtk/gui/gtk/signals.py
eQuimageGtk/gui/gtk/utils.py
eQuimageGtk/gui/misc/imagechooser.py
eQuimageGtk/gui/misc/utils.py
eQuimageGtk/gui/tools/addframe.py
eQuimageGtk/gui/tools/arcsinh.py
eQuimageGtk/gui/tools/bilateral.py
eQuimageGtk/gui/tools/blackpoint.py
eQuimageGtk/gui/tools/blend.py
eQuimageGtk/gui/tools/butterworth.py
eQuimageGtk/gui/tools/clahe.py
eQuimageGtk/gui/tools/colorbalance.py
eQuimageGtk/gui/tools/colornoise.py
eQuimageGtk/gui/tools/colorsaturation.py
eQuimageGtk/gui/tools/gaussian.py
eQuimageGtk/gui/tools/ghscolorsat.py
eQuimageGtk/gui/tools/grayscale.py
eQuimageGtk/gui/tools/hotpixels.py
eQuimageGtk/gui/tools/hyperbolic.py
eQuimageGtk/gui/tools/midtone.py
eQuimageGtk/gui/tools/nlmeans.py
eQuimageGtk/gui/tools/pixelmath.py
eQuimageGtk/gui/tools/resample.py
eQuimageGtk/gui/tools/stretch.py
eQuimageGtk/gui/tools/switch.py
eQuimageGtk/gui/tools/thresholdmask.py
eQuimageGtk/gui/tools/totalvariation.py
eQuimageGtk/gui/tools/unsharp.py
eQuimageGtk/gui/tools/wavelets.py
eQuimageGtk/icons/icon.ico
eQuimageGtk/icons/icon.png
eQuimageGtk/imageprocessing/Unistellar.py
eQuimageGtk/imageprocessing/colors.py
eQuimageGtk/imageprocessing/defs.py
eQuimageGtk/imageprocessing/imageprocessing.py
eQuimageGtk/imageprocessing/pixelmath.py
eQuimageGtk/imageprocessing/stretchfunctions.py
eQuimageGtk/imageprocessing/utils.py
eQuimageGtk/images/splash.png
equimage-1.7.0.dist-info/licenses/LICENSE
equimage-1.7.0.dist-info/METADATA
equimage-1.7.0.dist-info/WHEEL
equimage-1.7.0.dist-info/entry_points.txt
equimage-1.7.0.dist-info/top_level.txt
equimage-1.7.0.dist-info/RECORD
