Metadata-Version: 2.4
Name: eQuimage
Version: 1.7.0
Summary: eQuimage is a tool to postprocess astronomical images from Unistellar telescopes.
Author-email: Yann-Michel Niquet <contact@ymniquet.fr>
License-Expression: GPL-3.0-or-later
Project-URL: homepage, https://astro.ymniquet.fr/
Project-URL: repository, https://github.com/ymniquet/eQuimage
Classifier: Programming Language :: Python :: 3
Classifier: Operating System :: OS Independent
Requires-Python: >=3.7
License-File: LICENSE
Requires-Dist: numpy
Requires-Dist: matplotlib>=3.0
Requires-Dist: scipy
Requires-Dist: pywavelets
Requires-Dist: pillow
Requires-Dist: tifffile
Requires-Dist: imagecodecs
Requires-Dist: astropy
Requires-Dist: scikit-image>=0.21.0
Requires-Dist: PyGObject>=3.0
Requires-Dist: dask
Dynamic: license-file
